{
    "patches": [
        {
            "label": "2026-03-16_16-13-05",
            "content": "@@ -98,17 +98,21 @@\n (%22%25s\n-%22\n+ %25d%22,\n  &pessoa\n )%0A  \n@@ -111,28 +111,9 @@\n ssoa\n-)%0A    fmt.scanf(%22%25d%22\n+,\n  &id\n",
            "lines": "28"
        },
        {
            "label": "2026-03-16_16-14-07",
            "content": "@@ -96,17 +96,17 @@\n nf(%22%25s%22 \n- \n+&\n pessoa)%0A\n",
            "lines": "29"
        },
        {
            "label": "2026-03-16_16-14-41",
            "content": "@@ -89,17 +89,17 @@\n fmt.\n-S\n+s\n canf(%22%25s\n  %25d%22\n@@ -98,22 +98,37 @@\n (%22%25s\n- %25d%22, &pessoa,\n+%22  pessoa)%0A    fmt.scanf(%22%25d%22\n  &id\n@@ -167,33 +167,33 @@\n 2 %7B%0A        fmt.\n-P\n+p\n rintln(%22%25s eh cr\n@@ -240,33 +240,33 @@\n 8 %7B%0A        fmt.\n-P\n+p\n rintln(%22%25s eh jo\n@@ -311,33 +311,33 @@\n 5 %7B%0A        fmt.\n-P\n+p\n rintln(%22%25s eh ad\n@@ -385,33 +385,33 @@\n 0 %7B%0A        fmt.\n-P\n+p\n rintln(%22%25s eh id\n@@ -454,9 +454,9 @@\n fmt.\n-P\n+p\n rint\n",
            "lines": "29"
        },
        {
            "label": "2026-03-16_16-17-31",
            "content": "@@ -157,33 +157,34 @@\n        fmt.Print\n-f\n+ln\n (%22%25s eh crianca%5C\n@@ -182,18 +182,16 @@\n  crianca\n-%5Cn\n %22, pesso\n@@ -230,33 +230,34 @@\n        fmt.Print\n-f\n+ln\n (%22%25s eh jovem%5Cn%22\n@@ -253,18 +253,16 @@\n eh jovem\n-%5Cn\n %22, pesso\n@@ -301,33 +301,34 @@\n        fmt.Print\n-f\n+ln\n (%22%25s eh adulto%5Cn\n@@ -325,18 +325,16 @@\n h adulto\n-%5Cn\n %22, pesso\n@@ -375,33 +375,34 @@\n        fmt.Print\n-f\n+ln\n (%22%25s eh idoso%5Cn%22\n@@ -398,18 +398,16 @@\n eh idoso\n-%5Cn\n %22, pesso\n@@ -440,17 +440,18 @@\n mt.Print\n-f\n+ln\n (%22%25s eh \n@@ -459,10 +459,8 @@\n umia\n-%5Cn\n %22, p\n",
            "lines": "28"
        },
        {
            "label": "2026-03-16_16-18-29",
            "content": "@@ -185,32 +185,33 @@\n anca%5Cn%22, pessoa)\n+;\n %0A    %7D else if i\n@@ -257,32 +257,33 @@\n ovem%5Cn%22, pessoa)\n+;\n %0A    %7D else if i\n@@ -330,32 +330,33 @@\n ulto%5Cn%22, pessoa)\n+;\n %0A    %7D else if i\n@@ -408,24 +408,25 @@\n %5Cn%22, pessoa)\n+;\n %0A    %7D else \n",
            "lines": "28"
        },
        {
            "label": "2026-03-16_16-18-44",
            "content": "@@ -85,10 +85,8 @@\n     \n-//\n fmt.\n@@ -121,38 +121,8 @@\n de)%0A\n-    fmt.Scan(&pessoa, &idade)%0A\n     \n",
            "lines": "28"
        },
        {
            "label": "2026-03-16_16-22-13",
            "content": "@@ -35,24 +35,25 @@\n ain() %7B%0A\n+%0A\n     var \n nome Str\n@@ -48,14 +48,16 @@\n var \n-nome S\n+pessoa s\n trin\n@@ -66,42 +66,64 @@\n     \n-fmt.Scan(&nome)%0A%0A    var \n+var idade int%0A%0A    //fmt.Scanf(%22%25s %25d%22, &pessoa, &\n idade\n- int\n+)\n %0A   \n@@ -132,24 +132,33 @@\n mt.Scan(\n+&pessoa, \n &idade)%0A\n %0A    var\n@@ -153,37 +153,17 @@\n de)%0A\n-%0A\n     \n-var classificacao String\n+%0A    \n %0A%0A  \n@@ -192,32 +192,45 @@\n     \n-classificacao = %22idade%22%0A\n+fmt.Printf(%22%25s eh crianca%5Cn%22, pessoa)\n %0A   \n@@ -265,32 +265,43 @@\n     \n-classificacao = %22jovem%22%0A\n+fmt.Printf(%22%25s eh jovem%5Cn%22, pessoa)\n %0A   \n@@ -336,33 +336,44 @@\n     \n-classificacao = %22adulto%22%0A\n+fmt.Printf(%22%25s eh adulto%5Cn%22, pessoa)\n %0A   \n@@ -410,134 +410,112 @@\n     \n-classificacao = %22idoso%22%0A%0A    %7D else %7B%0A        classificacao = %22mumia%22%0A    %7D%0A%0A    fmt.Printf(%22%25s eh %25s%5Cn%22, nome, classificacao)%0A\n+fmt.Printf(%22%25s eh idoso%5Cn%22, pessoa)%0A    %7D else %7B%0A        fmt.Printf(%22%25s eh mumia%5Cn%22, pessoa)%0A    %7D%0A%0A%0A    \n %0A%7D%0A\n",
            "lines": "29"
        },
        {
            "label": "2026-04-03_00-35-03",
            "content": "@@ -68,16 +68,17 @@\n mt.Scan(\n+&\n nome)%0A%0A \n@@ -107,16 +107,17 @@\n mt.Scan(\n+&\n idade)%0A%0A\n",
            "lines": "32"
        },
        {
            "label": "2026-04-03_00-35-27",
            "content": "@@ -48,17 +48,17 @@\n ar nome \n-s\n+S\n tring%0A  \n@@ -68,17 +68,16 @@\n mt.Scan(\n-&\n nome)%0A%0A \n@@ -110,9 +110,8 @@\n can(\n-&\n idad\n@@ -136,17 +136,17 @@\n ficacao \n-s\n+S\n tring%0A%0A \n",
            "lines": "32"
        },
        {
            "label": "2026-04-03_00-37-19",
            "content": "@@ -195,15 +195,13 @@\n  = %22\n-crianca\n+idade\n %22%0A%0A \n",
            "lines": "32"
        },
        {
            "label": "2026-04-03_00-38-18",
            "content": "package main\n\nimport \"fmt\"\n\nfunc main() {\n    var nome string\n    fmt.Scan(&nome)\n\n    var idade int\n    fmt.Scan(&idade)\n\n    var classificacao string\n\n    if idade < 12 {\n        classificacao = \"crianca\"\n\n    } else if idade < 18 {\n        classificacao = \"jovem\"\n\n    } else if idade < 65 {\n        classificacao = \"adulto\"\n\n    } else if idade < 1000 {\n        classificacao = \"idoso\"\n\n    } else {\n        classificacao = \"mumia\"\n    }\n\n    fmt.Printf(\"%s eh %s\\n\", nome, classificacao)\n\n}\n",
            "lines": "32"
        }
    ]
}